kv_pdf_processor/pdf_splitter.py
kv_pdf_processor/pdf_to_image.py
kv_pdf_processor-0.1.2.dist-info/METADATA
kv_pdf_processor-0.1.2.dist-info/WHEEL
kv_pdf_processor-0.1.2.dist-info/top_level.txt
kv_pdf_processor-0.1.2.dist-info/RECORD
