Metadata-Version: 2.1
Name: kv-pdf-processor
Version: 0.1.2
Author-email: Justin Bui <jmbui@klangverso.com>
Requires-Python: >=3.8
Requires-Dist: PyPDF2
Requires-Dist: pymupdf
Requires-Dist: datetime
